{
  "$schemaVersion": "skills_melee_v3",
  "meta": {
    "title": "玩家技能树 Growth v1 - 五主干重编排工作稿",
    "variantId": "growth_v1_five_tracks",
    "status": "authoring_review",
    "source": "assets/data/skills_melee_v4_5.json",
    "buffsPath": "assets/data/buffs_v2_7.json",
    "notes": [
      "本工作稿不发布到主流程，用于在技能编辑器中评审新的成长树结构。",
      "目标是复用现有技能效果和理念，重排为剑系、锤系、法术系、防御系、战术/AP系五条主干。",
      "节点名称和描述已从测试期表达调整为面向玩家的正式表达，后续确认后再进入运行时平衡。"
    ],
    "growthTracks": [
      {
        "id": "sword",
        "label": "剑系",
        "summary": "快攻、多段、流血、撕裂与吸血收割。",
        "x": 220
      },
      {
        "id": "hammer",
        "label": "锤系",
        "summary": "重击、破甲、击晕、范围压制与终结重击。",
        "x": 460
      },
      {
        "id": "spell",
        "label": "法术系",
        "summary": "毒、冰、虚弱、易伤与 AP 诅咒等状态控制。",
        "x": 700
      },
      {
        "id": "defense",
        "label": "防御系",
        "summary": "补甲、备甲、减伤、防反与反伤。",
        "x": 940
      },
      {
        "id": "tempo",
        "label": "战术/AP系",
        "summary": "速度、免伤、回 AP 与技能费用压缩。",
        "x": 1340
      }
    ],
    "defaultParts": [
      "head",
      "chest",
      "abdomen",
      "arm",
      "leg"
    ],
    "enums": {
      "rarities": [
        "Common",
        "Uncommon",
        "Rare",
        "Epic",
        "Legendary"
      ],
      "targetSubjects": [
        "SUBJECT_SELF",
        "SUBJECT_ENEMY",
        "SUBJECT_BOTH"
      ],
      "targetScopes": [
        "SCOPE_ENTITY",
        "SCOPE_PART",
        "SCOPE_MULTI_PARTS"
      ],
      "selectionModes": [
        "single",
        "multiple",
        "random_single"
      ],
      "effectTypes": [
        "DMG_HP",
        "DMG_ARMOR",
        "PIERCE",
        "HEAL",
        "ARMOR_ADD",
        "AP_GAIN",
        "SPEED",
        "BUFF_APPLY",
        "BUFF_REMOVE"
      ],
      "amountTypes": [
        "ABS",
        "PCT_MAX",
        "PCT_CURRENT",
        "BUFF_STACKS"
      ],
      "buffRefTargets": [
        "self",
        "enemy"
      ],
      "requirementSelfPartModes": [
        "ANY",
        "ALL"
      ],
      "partOverrideModes": [
        "fixed",
        "listed"
      ],
      "hitModes": [
        "normal",
        "cannot_dodge",
        "always_crit"
      ],
      "repeat": {
        "minCount": 1,
        "maxCount": 20
      },
      "editStates": [
        "done",
        "editing",
        "deprecated"
      ]
    }
  },
  "skills": [
    {
      "id": "skill_double_thrust",
      "name": "剑击",
      "rarity": "Common",
      "description": "基础剑技。快速连续攻击目标部位，适合作为剑系构筑的稳定起手。",
      "prerequisites": [],
      "unlock": {
        "cost": {
          "kp": 1
        },
        "requirements": {},
        "exclusives": [],
        "grants": {
          "type": "permanent"
        }
      },
      "editorMeta": {
        "x": 214,
        "y": 214,
        "group": "剑系",
        "locked": false,
        "editState": "done",
        "groupLabel": "剑系",
        "growthTrack": "sword",
        "growthTier": 1,
        "sourceSkillId": "skill_double_thrust"
      },
      "speed": 4,
      "target": {
        "subject": "SUBJECT_ENEMY",
        "scope": "SCOPE_PART",
        "selection": {
          "mode": "random_single",
          "candidateParts": [
            "head",
            "chest",
            "abdomen",
            "arm",
            "leg"
          ],
          "selectedParts": [],
          "selectCount": 1
        }
      },
      "requirements": {
        "selfPart": {
          "mode": "ANY",
          "parts": [
            "arm"
          ],
          "mustBeUsable": true
        }
      },
      "costs": {
        "ap": 1,
        "partSlot": {
          "part": "arm",
          "slotCost": 1
        },
        "perTurnLimit": 1
      },
      "buffRefs": {
        "apply": [],
        "remove": []
      },
      "actions": [
        {
          "id": "action_1",
          "name": "Effect 1",
          "target": {
            "binding": {
              "mode": "follow",
              "ref": "skillTarget"
            }
          },
          "effect": {
            "effectType": "DMG_HP",
            "amountType": "ABS",
            "repeat": {
              "count": 2
            },
            "amount": 10
          }
        }
      ]
    },
    {
      "id": "skill_1771769351059",
      "name": "锯齿斩",
      "rarity": "Uncommon",
      "costs": {
        "ap": 1,
        "perTurnLimit": 1
      },
      "speed": 0,
      "target": {
        "subject": "SUBJECT_ENEMY",
        "scope": "SCOPE_PART",
        "selection": {
          "mode": "single",
          "candidateParts": [
            "head",
            "chest",
            "abdomen",
            "arm",
            "leg"
          ],
          "selectedParts": [],
          "selectCount": 1
        }
      },
      "prerequisites": [
        "skill_double_thrust"
      ],
      "buffRefs": {
        "apply": [
          {
            "buffId": "buff_bleed",
            "target": "enemy",
            "params": {
              "buff_duration": 2,
              "maxVal": 5
            }
          }
        ],
        "remove": []
      },
      "actions": [
        {
          "id": "action_1",
          "name": "伤害",
          "target": {
            "binding": {
              "mode": "follow",
              "ref": "skillTarget"
            }
          },
          "effect": {
            "effectType": "DMG_HP",
            "amountType": "ABS",
            "amount": 5
          }
        }
      ],
      "editorMeta": {
        "x": 214,
        "y": 414,
        "group": "剑系",
        "locked": false,
        "editState": "done",
        "groupLabel": "剑系",
        "growthTrack": "sword",
        "growthTier": 2,
        "sourceSkillId": "skill_1771769351059"
      },
      "description": "进阶剑技。造成少量伤害并施加流血，让剑系开始拥有持续压制能力。",
      "unlock": {
        "cost": {
          "kp": 2
        },
        "requirements": {},
        "exclusives": [],
        "grants": {
          "type": "permanent"
        }
      },
      "requirements": {}
    },
    {
      "id": "skill_shockwave_copy_1770042951717",
      "name": "撕裂伤口",
      "rarity": "Rare",
      "description": "流血强化。让目标伤口持续恶化，为后续血系爆发创造窗口。",
      "prerequisites": [
        "skill_1771769351059"
      ],
      "unlock": {
        "cost": {
          "kp": 3
        },
        "requirements": {},
        "exclusives": [],
        "grants": {
          "type": "permanent"
        }
      },
      "editorMeta": {
        "x": 214,
        "y": 614,
        "editState": "done",
        "group": "剑系",
        "locked": false,
        "groupLabel": "剑系",
        "growthTrack": "sword",
        "growthTier": 3,
        "sourceSkillId": "skill_shockwave_copy_1770042951717"
      },
      "speed": 8,
      "target": {
        "subject": "SUBJECT_ENEMY",
        "scope": "SCOPE_MULTI_PARTS",
        "selection": {
          "mode": "multiple",
          "candidateParts": [
            "head",
            "chest",
            "abdomen",
            "arm",
            "leg"
          ],
          "selectedParts": [
            "head",
            "chest",
            "abdomen",
            "arm",
            "leg"
          ],
          "selectCount": 5
        }
      },
      "requirements": {
        "selfPart": {
          "mode": "ANY",
          "parts": [
            "chest"
          ],
          "mustBeUsable": true
        }
      },
      "costs": {
        "ap": 1,
        "partSlot": {
          "part": "chest",
          "slotCost": 2
        },
        "perTurnLimit": 1
      },
      "buffRefs": {
        "apply": [
          {
            "buffId": "buff_tear_wound",
            "target": "enemy",
            "chance": 1,
            "duration": 2
          }
        ],
        "remove": []
      },
      "actions": [
        {
          "id": "action_1",
          "name": "Effect 1",
          "target": {
            "binding": {
              "mode": "follow",
              "ref": "skillTarget"
            }
          },
          "effect": {
            "effectType": "DMG_ARMOR",
            "amount": 5,
            "amountType": "ABS"
          }
        }
      ]
    },
    {
      "id": "skill_execute_copy_1770043820577",
      "name": "血涌斩",
      "rarity": "Epic",
      "description": "爆发剑技。根据目标流血层数造成伤害，把持续压制转化为一次打点。",
      "prerequisites": [
        "skill_shockwave_copy_1770042951717"
      ],
      "unlock": {
        "cost": {
          "kp": 5
        },
        "requirements": {},
        "exclusives": [],
        "grants": {
          "type": "permanent"
        }
      },
      "editorMeta": {
        "x": 114,
        "y": 814,
        "editState": "done",
        "group": "剑系",
        "locked": false,
        "groupLabel": "剑系",
        "growthTrack": "sword",
        "growthTier": 4,
        "sourceSkillId": "skill_execute_copy_1770043820577"
      },
      "speed": 1,
      "target": {
        "subject": "SUBJECT_ENEMY",
        "scope": "SCOPE_PART",
        "selection": {
          "mode": "single",
          "candidateParts": [
            "head",
            "chest",
            "abdomen",
            "arm",
            "leg"
          ],
          "selectedParts": [],
          "selectCount": 1
        }
      },
      "requirements": {
        "targetHpPercentBelow": 0.3
      },
      "costs": {
        "ap": 3,
        "partSlot": {
          "part": "arm",
          "slotCost": 2
        },
        "perTurnLimit": 1
      },
      "buffRefs": {
        "apply": [],
        "remove": []
      },
      "actions": [
        {
          "id": "action_1",
          "name": "Effect 1",
          "target": {
            "binding": {
              "mode": "follow",
              "ref": "skillTarget"
            }
          },
          "effect": {
            "effectType": "DMG_HP",
            "amount": 5,
            "amountType": "BUFF_STACKS",
            "amountSource": {
              "owner": "skillTarget",
              "buffId": "buff_bleed",
              "multiplier": 5,
              "missingAs": 0
            },
            "note": "按目标流血层数造成伤害；当前不消耗流血层数。"
          }
        }
      ]
    },
    {
      "id": "skill_execute_copy_1770044052832",
      "name": "饮血斩",
      "rarity": "Epic",
      "description": "续航剑技。根据目标流血层数回复自身生命，让流血构筑具备回合续航。",
      "prerequisites": [
        "skill_shockwave_copy_1770042951717"
      ],
      "unlock": {
        "cost": {
          "kp": 5
        },
        "requirements": {},
        "exclusives": [],
        "grants": {
          "type": "permanent"
        }
      },
      "editorMeta": {
        "x": 214,
        "y": 814,
        "editState": "done",
        "group": "剑系",
        "locked": false,
        "groupLabel": "剑系",
        "growthTrack": "sword",
        "growthTier": 5,
        "sourceSkillId": "skill_execute_copy_1770044052832"
      },
      "speed": 3,
      "target": {
        "subject": "SUBJECT_ENEMY",
        "scope": "SCOPE_PART",
        "selection": {
          "mode": "single",
          "candidateParts": [
            "head",
            "chest",
            "abdomen",
            "arm",
            "leg"
          ],
          "selectedParts": [],
          "selectCount": 1
        }
      },
      "requirements": {
        "targetHpPercentBelow": 0.3
      },
      "costs": {
        "ap": 3,
        "partSlot": {
          "part": "arm",
          "slotCost": 2
        },
        "perTurnLimit": 1
      },
      "buffRefs": {
        "apply": [],
        "remove": []
      },
      "actions": [
        {
          "id": "action_1",
          "name": "Effect 1",
          "target": {
            "binding": {
              "mode": "explicit"
            },
            "spec": {
              "subject": "SUBJECT_SELF",
              "scope": "SCOPE_ENTITY",
              "selection": {
                "mode": "single",
                "candidateParts": [],
                "selectedParts": [],
                "selectCount": 1
              }
            }
          },
          "effect": {
            "effectType": "HEAL",
            "amount": 2,
            "amountType": "BUFF_STACKS",
            "amountSource": {
              "owner": "skillTarget",
              "buffId": "buff_bleed",
              "multiplier": 4,
              "missingAs": 0
            },
            "note": "按目标流血层数回复自身 HP；当前不消耗流血层数。"
          }
        }
      ]
    },
    {
      "id": "skill_blood_debt_due",
      "name": "猩红收割",
      "rarity": "Legendary",
      "description": "剑系终局。把流血压制转成持续吸血，形成越打越稳的收割节奏。",
      "prerequisites": [
        "skill_execute_copy_1770044052832"
      ],
      "unlock": {
        "cost": {
          "kp": 8
        },
        "requirements": {},
        "exclusives": [],
        "grants": {
          "type": "permanent"
        }
      },
      "editorMeta": {
        "x": 214,
        "y": 1014,
        "group": "剑系",
        "locked": false,
        "editState": "done",
        "groupLabel": "剑系",
        "growthTrack": "sword",
        "growthTier": 6,
        "sourceSkillId": "skill_blood_debt_due"
      },
      "speed": 1,
      "target": {
        "subject": "SUBJECT_SELF",
        "scope": "SCOPE_ENTITY",
        "selection": {
          "mode": "single",
          "candidateParts": [],
          "selectedParts": [],
          "selectCount": 1
        }
      },
      "requirements": {},
      "costs": {
        "ap": 2,
        "perTurnLimit": 1
      },
      "buffRefs": {
        "apply": [
          {
            "buffId": "buff_lifesteal",
            "target": "self",
            "chance": 1,
            "duration": 3
          }
        ],
        "remove": []
      },
      "actions": []
    },
    {
      "id": "skill_1770474698976",
      "name": "血誓打击",
      "rarity": "Legendary",
      "costs": {
        "ap": 1,
        "perTurnLimit": 1
      },
      "speed": 5,
      "target": {
        "subject": "SUBJECT_ENEMY",
        "scope": "SCOPE_PART",
        "selection": {
          "mode": "single",
          "candidateParts": [
            "head",
            "chest",
            "abdomen",
            "arm",
            "leg"
          ],
          "selectedParts": [],
          "selectCount": 1
        }
      },
      "prerequisites": [
        "skill_blood_debt_due"
      ],
      "buffRefs": {
        "apply": [],
        "remove": []
      },
      "editorMeta": {
        "x": 214,
        "y": 1114,
        "editState": "done",
        "group": "剑系",
        "locked": false,
        "groupLabel": "剑系",
        "growthTrack": "sword",
        "growthTier": 7,
        "sourceSkillId": "skill_1770474698976"
      },
      "description": "高阶剑技。牺牲少量生命换取直接伤害，适合吸血成型后的主动爆发。",
      "unlock": {
        "cost": {
          "kp": 8
        },
        "requirements": {},
        "exclusives": [],
        "grants": {
          "type": "permanent"
        }
      },
      "requirements": {},
      "actions": [
        {
          "id": "action_1",
          "name": "自己掉血",
          "target": {
            "binding": {
              "mode": "explicit"
            },
            "spec": {
              "subject": "SUBJECT_SELF",
              "scope": "SCOPE_ENTITY",
              "selection": {
                "mode": "single",
                "candidateParts": [
                  "head",
                  "chest",
                  "abdomen",
                  "arm",
                  "leg"
                ],
                "selectedParts": [],
                "selectCount": 1
              }
            }
          },
          "effect": {
            "effectType": "DMG_HP",
            "amountType": "ABS",
            "amount": 2
          }
        },
        {
          "id": "action_2",
          "name": "伤害敌人",
          "target": {
            "binding": {
              "mode": "follow",
              "ref": "skillTarget"
            }
          },
          "effect": {
            "effectType": "DMG_HP",
            "amountType": "ABS",
            "amount": 20
          }
        }
      ]
    },
    {
      "id": "skill_heavy_swing",
      "name": "锤击",
      "rarity": "Common",
      "description": "基础锤技。对目标部位造成稳定重击伤害，是锤系破甲路线的起点。",
      "prerequisites": [],
      "unlock": {
        "cost": {
          "kp": 1
        },
        "requirements": {},
        "exclusives": [],
        "grants": {
          "type": "permanent"
        }
      },
      "editorMeta": {
        "x": 414,
        "y": 214,
        "group": "锤系",
        "locked": false,
        "editState": "done",
        "groupLabel": "锤系",
        "growthTrack": "hammer",
        "growthTier": 1,
        "sourceSkillId": "skill_heavy_swing"
      },
      "speed": 0,
      "placement": {
        "maxSlots": 1
      },
      "target": {
        "subject": "SUBJECT_ENEMY",
        "scope": "SCOPE_PART",
        "selection": {
          "mode": "single",
          "candidateParts": [
            "head",
            "chest",
            "abdomen",
            "arm",
            "leg"
          ],
          "selectedParts": [],
          "selectCount": 1
        }
      },
      "requirements": {
        "selfPart": {
          "mode": "ANY",
          "parts": [
            "arm"
          ],
          "mustBeUsable": true
        }
      },
      "costs": {
        "ap": 2,
        "partSlot": {
          "part": "arm",
          "slotCost": 2
        },
        "perTurnLimit": 1
      },
      "buffRefs": {
        "apply": [],
        "remove": []
      },
      "actions": [
        {
          "id": "action_1",
          "name": "Effect 1",
          "target": {
            "binding": {
              "mode": "follow",
              "ref": "skillTarget"
            }
          },
          "effect": {
            "effectType": "DMG_HP",
            "amountType": "ABS",
            "amount": 20
          }
        }
      ]
    },
    {
      "id": "skill_skull_cracker",
      "name": "破甲重锤",
      "rarity": "Uncommon",
      "description": "进阶锤技。集中打击头部护甲，强化锤系针对重甲目标的定位。",
      "prerequisites": [
        "skill_heavy_swing"
      ],
      "unlock": {
        "cost": {
          "kp": 2
        },
        "requirements": {},
        "exclusives": [],
        "grants": {
          "type": "permanent"
        }
      },
      "editorMeta": {
        "x": 414,
        "y": 414,
        "group": "锤系",
        "locked": false,
        "editState": "done",
        "groupLabel": "锤系",
        "growthTrack": "hammer",
        "growthTier": 2,
        "sourceSkillId": "skill_skull_cracker"
      },
      "speed": -3,
      "target": {
        "subject": "SUBJECT_ENEMY",
        "scope": "SCOPE_PART",
        "selection": {
          "mode": "single",
          "candidateParts": [
            "head"
          ],
          "selectedParts": [
            "head"
          ],
          "selectCount": 1
        }
      },
      "requirements": {
        "selfPart": {
          "mode": "ANY",
          "parts": [
            "arm"
          ],
          "mustBeUsable": true
        }
      },
      "costs": {
        "ap": 4,
        "partSlot": {
          "part": "arm",
          "slotCost": 2
        },
        "perTurnLimit": 1
      },
      "buffRefs": {
        "apply": [],
        "remove": []
      },
      "actions": [
        {
          "id": "action_2",
          "name": "Effect 2",
          "target": {
            "binding": {
              "mode": "follow",
              "ref": "skillTarget"
            }
          },
          "effect": {
            "effectType": "DMG_ARMOR",
            "amount": 20,
            "amountType": "ABS",
            "partOverride": {
              "mode": "fixed",
              "parts": [
                "head"
              ]
            }
          }
        }
      ]
    },
    {
      "id": "skill_hold_the_line",
      "name": "碎甲重拳",
      "rarity": "Rare",
      "description": "贴身重击。消耗自身护甲换取额外破甲，把防御资源转成进攻压力。",
      "prerequisites": [
        "skill_skull_cracker"
      ],
      "unlock": {
        "cost": {
          "kp": 3
        },
        "requirements": {},
        "exclusives": [],
        "grants": {
          "type": "permanent"
        }
      },
      "editorMeta": {
        "x": 414,
        "y": 614,
        "group": "锤系",
        "locked": false,
        "editState": "done",
        "groupLabel": "锤系",
        "growthTrack": "hammer",
        "growthTier": 3,
        "sourceSkillId": "skill_hold_the_line"
      },
      "speed": 2,
      "target": {
        "subject": "SUBJECT_ENEMY",
        "scope": "SCOPE_PART",
        "selection": {
          "mode": "single",
          "candidateParts": [
            "head",
            "chest",
            "abdomen",
            "arm",
            "leg"
          ],
          "selectedParts": [],
          "selectCount": 1
        }
      },
      "requirements": {
        "selfPart": {
          "mode": "ANY",
          "parts": [
            "chest"
          ],
          "mustBeUsable": true
        }
      },
      "costs": {
        "ap": 1,
        "perTurnLimit": 1
      },
      "buffRefs": {
        "apply": [],
        "remove": []
      },
      "actions": [
        {
          "id": "action_1",
          "name": "消耗护甲",
          "target": {
            "binding": {
              "mode": "explicit"
            },
            "spec": {
              "subject": "SUBJECT_SELF",
              "scope": "SCOPE_ENTITY",
              "selection": {
                "mode": "single",
                "candidateParts": [
                  "arm"
                ],
                "selectedParts": [
                  "arm"
                ],
                "selectCount": 1
              }
            }
          },
          "effect": {
            "effectType": "DMG_ARMOR",
            "amountType": "PCT_CURRENT",
            "amount": 50
          }
        },
        {
          "id": "action_2",
          "name": "造成伤害",
          "target": {
            "binding": {
              "mode": "follow",
              "ref": "skillTarget"
            }
          },
          "effect": {
            "effectType": "DMG_ARMOR",
            "amountType": "ABS",
            "amount": 20
          }
        }
      ]
    },
    {
      "id": "skill_execute_copy_1769961767095",
      "name": "卸甲",
      "rarity": "Epic",
      "description": "锤系关键节点。移除目标指定部位的大量护甲，为后续重击打开缺口。",
      "prerequisites": [
        "skill_hold_the_line"
      ],
      "unlock": {
        "cost": {
          "kp": 5
        },
        "requirements": {},
        "exclusives": [],
        "grants": {
          "type": "permanent"
        }
      },
      "editorMeta": {
        "x": 414,
        "y": 814,
        "editState": "done",
        "group": "锤系",
        "locked": false,
        "groupLabel": "锤系",
        "growthTrack": "hammer",
        "growthTier": 4,
        "sourceSkillId": "skill_execute_copy_1769961767095"
      },
      "speed": 1,
      "target": {
        "subject": "SUBJECT_ENEMY",
        "scope": "SCOPE_PART",
        "selection": {
          "mode": "single",
          "candidateParts": [
            "head",
            "chest",
            "abdomen",
            "arm",
            "leg"
          ],
          "selectedParts": [],
          "selectCount": 1
        }
      },
      "requirements": {},
      "costs": {
        "ap": 3,
        "partSlot": {
          "part": "arm",
          "slotCost": 2
        },
        "perTurnLimit": 1
      },
      "buffRefs": {
        "apply": [],
        "remove": []
      },
      "actions": [
        {
          "id": "action_1",
          "name": "Effect 1",
          "target": {
            "binding": {
              "mode": "follow",
              "ref": "skillTarget"
            }
          },
          "effect": {
            "effectType": "DMG_ARMOR",
            "amount": 100,
            "amountType": "PCT_CURRENT",
            "note": "按当前 HP 百分比造成伤害；引擎实现时可映射为 TRUE/PIERCE 以避免护甲干扰。"
          }
        }
      ]
    },
    {
      "id": "skill_earthquake",
      "name": "震地重击",
      "rarity": "Epic",
      "description": "重型压制。造成高额伤害并有概率眩晕，适合在破甲后扩大优势。",
      "prerequisites": [
        "skill_execute_copy_1769961767095"
      ],
      "unlock": {
        "cost": {
          "kp": 5
        },
        "requirements": {},
        "exclusives": [],
        "grants": {
          "type": "permanent"
        }
      },
      "editorMeta": {
        "x": 414,
        "y": 914,
        "group": "锤系",
        "locked": false,
        "editState": "done",
        "groupLabel": "锤系",
        "growthTrack": "hammer",
        "growthTier": 5,
        "sourceSkillId": "skill_earthquake"
      },
      "speed": -4,
      "target": {
        "subject": "SUBJECT_ENEMY",
        "scope": "SCOPE_PART",
        "selection": {
          "mode": "single",
          "candidateParts": [
            "head",
            "chest",
            "abdomen",
            "arm",
            "leg"
          ],
          "selectedParts": [],
          "selectCount": 1
        }
      },
      "requirements": {
        "selfPart": {
          "mode": "ANY",
          "parts": [
            "arm"
          ],
          "mustBeUsable": true
        }
      },
      "costs": {
        "ap": 5,
        "partSlot": {
          "part": "arm",
          "slotCost": 3
        },
        "perTurnLimit": 1
      },
      "buffRefs": {
        "apply": [
          {
            "buffId": "buff_stun",
            "target": "enemy",
            "chance": 0.5,
            "duration": 1
          }
        ],
        "remove": []
      },
      "actions": [
        {
          "id": "action_1",
          "name": "Effect 1",
          "target": {
            "binding": {
              "mode": "follow",
              "ref": "skillTarget"
            }
          },
          "effect": {
            "effectType": "DMG_HP",
            "amount": 50,
            "amountType": "ABS"
          }
        }
      ]
    },
    {
      "id": "skill_ragnarok",
      "name": "崩山终击",
      "rarity": "Legendary",
      "description": "锤系终局。以毁灭性多段重击压垮目标，承担高投入换取终结能力。",
      "prerequisites": [
        "skill_earthquake"
      ],
      "unlock": {
        "cost": {
          "kp": 8
        },
        "requirements": {},
        "exclusives": [],
        "grants": {
          "type": "permanent"
        }
      },
      "editorMeta": {
        "x": 414,
        "y": 1114,
        "group": "锤系",
        "locked": false,
        "editState": "done",
        "groupLabel": "锤系",
        "growthTrack": "hammer",
        "growthTier": 6,
        "sourceSkillId": "skill_ragnarok"
      },
      "speed": -5,
      "target": {
        "subject": "SUBJECT_ENEMY",
        "scope": "SCOPE_MULTI_PARTS",
        "selection": {
          "mode": "multiple",
          "candidateParts": [
            "head",
            "chest",
            "abdomen",
            "arm",
            "leg"
          ],
          "selectedParts": [
            "head",
            "chest",
            "abdomen",
            "arm",
            "leg"
          ],
          "selectCount": 5
        }
      },
      "requirements": {
        "selfPart": {
          "mode": "ANY",
          "parts": [
            "arm"
          ],
          "mustBeUsable": true
        }
      },
      "costs": {
        "ap": 3,
        "partSlot": {
          "part": "arm",
          "slotCost": 4
        },
        "perTurnLimit": 1
      },
      "buffRefs": {
        "apply": [],
        "remove": []
      },
      "actions": [
        {
          "id": "action_1",
          "name": "Effect 1",
          "target": {
            "binding": {
              "mode": "follow",
              "ref": "skillTarget"
            }
          },
          "effect": {
            "effectType": "DMG_HP",
            "amountType": "ABS",
            "repeat": {
              "count": 6
            },
            "amount": 50
          }
        }
      ]
    },
    {
      "id": "skill_leftover_lunchbox",
      "name": "毒雾术",
      "rarity": "Common",
      "description": "基础法术。造成少量伤害并施加中毒，让法术系从持续伤害起步。",
      "prerequisites": [],
      "unlock": {
        "cost": {
          "kp": 1
        },
        "requirements": {},
        "exclusives": [],
        "grants": {
          "type": "permanent"
        }
      },
      "editorMeta": {
        "x": 614,
        "y": 214,
        "group": "法术系",
        "locked": false,
        "editState": "done",
        "groupLabel": "法术系",
        "growthTrack": "spell",
        "growthTier": 1,
        "sourceSkillId": "skill_leftover_lunchbox"
      },
      "speed": 0,
      "target": {
        "subject": "SUBJECT_ENEMY",
        "scope": "SCOPE_PART",
        "selection": {
          "mode": "single",
          "candidateParts": [
            "head",
            "chest",
            "abdomen",
            "arm",
            "leg"
          ],
          "selectedParts": [],
          "selectCount": 1
        }
      },
      "requirements": {},
      "costs": {
        "ap": 1,
        "perTurnLimit": 1
      },
      "buffRefs": {
        "apply": [
          {
            "buffId": "buff_poison",
            "target": "enemy",
            "chance": 1,
            "duration": 3,
            "params": {
              "damageVal": 5
            }
          }
        ],
        "remove": []
      },
      "actions": [
        {
          "id": "action_1",
          "name": "砸盒饭",
          "target": {
            "binding": {
              "mode": "follow",
              "ref": "skillTarget"
            }
          },
          "effect": {
            "effectType": "DMG_HP",
            "amountType": "ABS",
            "amount": 4
          }
        }
      ]
    },
    {
      "id": "skill_loose_shoelaces",
      "name": "寒霜缠绕",
      "rarity": "Uncommon",
      "description": "控制法术。造成少量伤害并降低目标速度，让敌人的行动节奏变慢。",
      "prerequisites": [
        "skill_leftover_lunchbox"
      ],
      "unlock": {
        "cost": {
          "kp": 2
        },
        "requirements": {},
        "exclusives": [],
        "grants": {
          "type": "permanent"
        }
      },
      "editorMeta": {
        "x": 614,
        "y": 414,
        "group": "法术系",
        "locked": false,
        "editState": "done",
        "groupLabel": "法术系",
        "growthTrack": "spell",
        "growthTier": 2,
        "sourceSkillId": "skill_loose_shoelaces"
      },
      "speed": 1,
      "target": {
        "subject": "SUBJECT_ENEMY",
        "scope": "SCOPE_PART",
        "selection": {
          "mode": "single",
          "candidateParts": [
            "head",
            "chest",
            "abdomen",
            "arm",
            "leg"
          ],
          "selectedParts": [],
          "selectCount": 1
        }
      },
      "requirements": {},
      "costs": {
        "ap": 1,
        "perTurnLimit": 1
      },
      "buffRefs": {
        "apply": [
          {
            "buffId": "buff_slow",
            "target": "enemy",
            "chance": 1,
            "duration": 2,
            "params": {
              "buff_speedVal": -4
            }
          }
        ],
        "remove": []
      },
      "actions": [
        {
          "id": "action_1",
          "name": "绊一脚",
          "target": {
            "binding": {
              "mode": "follow",
              "ref": "skillTarget"
            }
          },
          "effect": {
            "effectType": "DMG_HP",
            "amountType": "ABS",
            "amount": 5
          }
        }
      ]
    },
    {
      "id": "skill_all_talk_weak_legs",
      "name": "虚弱诅咒",
      "rarity": "Epic",
      "description": "削弱法术。降低目标攻击能力，让法术系具备降低压力的手段。",
      "prerequisites": [
        "skill_break_defense_comment"
      ],
      "unlock": {
        "cost": {
          "kp": 5
        },
        "requirements": {},
        "exclusives": [],
        "grants": {
          "type": "permanent"
        }
      },
      "editorMeta": {
        "x": 614,
        "y": 814,
        "group": "法术系",
        "locked": false,
        "editState": "done",
        "groupLabel": "法术系",
        "growthTrack": "spell",
        "growthTier": 4,
        "sourceSkillId": "skill_all_talk_weak_legs"
      },
      "speed": 0,
      "target": {
        "subject": "SUBJECT_ENEMY",
        "scope": "SCOPE_ENTITY",
        "selection": {
          "mode": "single",
          "candidateParts": [],
          "selectedParts": [],
          "selectCount": 1
        }
      },
      "requirements": {},
      "costs": {
        "ap": 2,
        "perTurnLimit": 1
      },
      "buffRefs": {
        "apply": [
          {
            "buffId": "debuff_weak",
            "target": "enemy",
            "chance": 1,
            "duration": 2
          }
        ],
        "remove": []
      },
      "actions": []
    },
    {
      "id": "skill_break_defense_comment",
      "name": "易伤符印",
      "rarity": "Rare",
      "description": "增伤法术。给目标施加易伤，让后续物理或法术爆发更有效。",
      "prerequisites": [
        "skill_loose_shoelaces"
      ],
      "unlock": {
        "cost": {
          "kp": 3
        },
        "requirements": {},
        "exclusives": [],
        "grants": {
          "type": "permanent"
        }
      },
      "editorMeta": {
        "x": 614,
        "y": 614,
        "group": "法术系",
        "locked": false,
        "editState": "done",
        "groupLabel": "法术系",
        "growthTrack": "spell",
        "growthTier": 3,
        "sourceSkillId": "skill_break_defense_comment"
      },
      "speed": 0,
      "target": {
        "subject": "SUBJECT_ENEMY",
        "scope": "SCOPE_PART",
        "selection": {
          "mode": "single",
          "candidateParts": [
            "head",
            "chest",
            "abdomen",
            "arm",
            "leg"
          ],
          "selectedParts": [],
          "selectCount": 1
        }
      },
      "requirements": {},
      "costs": {
        "ap": 1,
        "perTurnLimit": 1
      },
      "buffRefs": {
        "apply": [
          {
            "buffId": "buff_vulnerable",
            "target": "enemy",
            "chance": 1,
            "duration": 2
          }
        ],
        "remove": []
      },
      "actions": [
        {
          "id": "action_1",
          "name": "扎心",
          "target": {
            "binding": {
              "mode": "follow",
              "ref": "skillTarget"
            }
          },
          "effect": {
            "effectType": "DMG_HP",
            "amountType": "ABS",
            "amount": 5
          }
        }
      ]
    },
    {
      "id": "skill_forced_overtime",
      "name": "时间诅咒",
      "rarity": "Legendary",
      "description": "高阶法术。提高目标后续技能 AP 开销，从资源层面压制敌人。",
      "prerequisites": [
        "skill_all_talk_weak_legs"
      ],
      "unlock": {
        "cost": {
          "kp": 8
        },
        "requirements": {},
        "exclusives": [],
        "grants": {
          "type": "permanent"
        }
      },
      "editorMeta": {
        "x": 614,
        "y": 1014,
        "group": "法术系",
        "locked": false,
        "editState": "done",
        "groupLabel": "法术系",
        "growthTrack": "spell",
        "growthTier": 5,
        "sourceSkillId": "skill_forced_overtime"
      },
      "speed": 0,
      "target": {
        "subject": "SUBJECT_ENEMY",
        "scope": "SCOPE_ENTITY",
        "selection": {
          "mode": "single",
          "candidateParts": [],
          "selectedParts": [],
          "selectCount": 1
        }
      },
      "requirements": {},
      "costs": {
        "ap": 2,
        "perTurnLimit": 1
      },
      "buffRefs": {
        "apply": [
          {
            "buffId": "new_buff_1771487055554",
            "target": "enemy",
            "chance": 1,
            "duration": 3
          }
        ],
        "remove": []
      },
      "actions": []
    },
    {
      "id": "skill_block",
      "name": "修理护甲",
      "rarity": "Common",
      "description": "基础防御。指定部位获得护甲，是防御系所有后续护甲构筑的起点。",
      "prerequisites": [],
      "unlock": {
        "cost": {
          "kp": 1
        },
        "requirements": {},
        "exclusives": [],
        "grants": {
          "type": "permanent"
        }
      },
      "editorMeta": {
        "x": 1114,
        "y": 214,
        "group": "防御系",
        "locked": false,
        "editState": "done",
        "groupLabel": "防御系",
        "growthTrack": "defense",
        "growthTier": 1,
        "sourceSkillId": "skill_block"
      },
      "speed": 5,
      "target": {
        "subject": "SUBJECT_SELF",
        "scope": "SCOPE_PART",
        "selection": {
          "mode": "single",
          "candidateParts": [
            "head",
            "chest",
            "abdomen",
            "arm",
            "leg"
          ],
          "selectedParts": [],
          "selectCount": 1
        }
      },
      "requirements": {
        "selfPart": {
          "mode": "ANY",
          "parts": [
            "arm"
          ],
          "mustBeUsable": true
        }
      },
      "costs": {
        "ap": 1,
        "perTurnLimit": 1
      },
      "buffRefs": {
        "apply": [],
        "remove": []
      },
      "actions": [
        {
          "id": "action_1",
          "name": "Effect 1",
          "target": {
            "binding": {
              "mode": "follow",
              "ref": "skillTarget"
            }
          },
          "effect": {
            "effectType": "ARMOR_ADD",
            "amountType": "ABS",
            "amount": 10
          }
        }
      ]
    },
    {
      "id": "skill_artery_slice_copy_1769788322314",
      "name": "护臂加固",
      "rarity": "Uncommon",
      "description": "部位防御。强化手臂护甲，支撑需要手臂发力的攻击和防反技能。",
      "prerequisites": [
        "skill_block"
      ],
      "unlock": {
        "cost": {
          "kp": 1
        },
        "requirements": {},
        "exclusives": [],
        "grants": {
          "type": "permanent"
        }
      },
      "editorMeta": {
        "x": 1014,
        "y": 414,
        "editState": "done",
        "group": "防御系",
        "locked": false,
        "groupLabel": "防御系",
        "growthTrack": "defense",
        "growthTier": 2,
        "sourceSkillId": "skill_artery_slice_copy_1769788322314"
      },
      "speed": 2,
      "target": {
        "subject": "SUBJECT_SELF",
        "scope": "SCOPE_PART",
        "selection": {
          "mode": "single",
          "candidateParts": [
            "arm"
          ],
          "selectedParts": [],
          "selectCount": 1
        }
      },
      "requirements": {
        "selfPart": {
          "mode": "ANY",
          "parts": [
            "arm"
          ],
          "mustBeUsable": true
        }
      },
      "costs": {
        "ap": 1,
        "partSlot": {
          "part": "arm",
          "slotCost": 1
        },
        "perTurnLimit": 1
      },
      "buffRefs": {
        "apply": [],
        "remove": []
      },
      "actions": [
        {
          "id": "action_1",
          "name": "Effect 1",
          "target": {
            "binding": {
              "mode": "follow",
              "ref": "skillTarget"
            }
          },
          "effect": {
            "effectType": "ARMOR_ADD",
            "amount": 15,
            "amountType": "ABS"
          }
        }
      ]
    },
    {
      "id": "skill_artery_slice",
      "name": "头盔加固",
      "rarity": "Uncommon",
      "description": "部位防御。强化头部护甲，降低被点杀或控制窗口打开的风险。",
      "prerequisites": [
        "skill_block"
      ],
      "unlock": {
        "cost": {
          "kp": 1
        },
        "requirements": {},
        "exclusives": [],
        "grants": {
          "type": "permanent"
        }
      },
      "editorMeta": {
        "x": 1314,
        "y": 414,
        "group": "防御系",
        "locked": false,
        "editState": "done",
        "groupLabel": "防御系",
        "growthTrack": "defense",
        "growthTier": 2,
        "sourceSkillId": "skill_artery_slice"
      },
      "speed": 2,
      "target": {
        "subject": "SUBJECT_SELF",
        "scope": "SCOPE_PART",
        "selection": {
          "mode": "single",
          "candidateParts": [
            "head"
          ],
          "selectedParts": [
            "head"
          ],
          "selectCount": 1
        }
      },
      "requirements": {
        "selfPart": {
          "mode": "ANY",
          "parts": [
            "arm"
          ],
          "mustBeUsable": true
        }
      },
      "costs": {
        "ap": 1,
        "partSlot": {
          "part": "head",
          "slotCost": 1
        },
        "perTurnLimit": 1
      },
      "buffRefs": {
        "apply": [],
        "remove": []
      },
      "actions": [
        {
          "id": "action_1",
          "name": "Effect 1",
          "target": {
            "binding": {
              "mode": "follow",
              "ref": "skillTarget"
            }
          },
          "effect": {
            "effectType": "ARMOR_ADD",
            "amount": 20,
            "amountType": "ABS"
          }
        }
      ]
    },
    {
      "id": "skill_artery_slice_copy_1769789197982",
      "name": "护腿加固",
      "rarity": "Uncommon",
      "description": "部位防御。强化腿部护甲，保护速度和战术移动相关能力。",
      "prerequisites": [
        "skill_block"
      ],
      "unlock": {
        "cost": {
          "kp": 1
        },
        "requirements": {},
        "exclusives": [],
        "grants": {
          "type": "permanent"
        }
      },
      "editorMeta": {
        "x": 1214,
        "y": 414,
        "editState": "done",
        "group": "防御系",
        "locked": false,
        "groupLabel": "防御系",
        "growthTrack": "defense",
        "growthTier": 2,
        "sourceSkillId": "skill_artery_slice_copy_1769789197982"
      },
      "speed": 2,
      "target": {
        "subject": "SUBJECT_SELF",
        "scope": "SCOPE_PART",
        "selection": {
          "mode": "single",
          "candidateParts": [
            "leg"
          ],
          "selectedParts": [],
          "selectCount": 1
        }
      },
      "requirements": {
        "selfPart": {
          "mode": "ANY",
          "parts": [
            "arm"
          ],
          "mustBeUsable": true
        }
      },
      "costs": {
        "ap": 1,
        "partSlot": {
          "part": "leg",
          "slotCost": 1
        },
        "perTurnLimit": 1
      },
      "buffRefs": {
        "apply": [],
        "remove": []
      },
      "actions": [
        {
          "id": "action_1",
          "name": "Effect 1",
          "target": {
            "binding": {
              "mode": "follow",
              "ref": "skillTarget"
            }
          },
          "effect": {
            "effectType": "ARMOR_ADD",
            "amount": 20,
            "amountType": "ABS"
          }
        }
      ]
    },
    {
      "id": "skill_heal",
      "name": "急救",
      "rarity": "Common",
      "description": "恢复技能。回复生命值，作为防御系处理失误和持久战的基础兜底。",
      "prerequisites": [
        "skill_block"
      ],
      "unlock": {
        "cost": {
          "kp": 1
        },
        "requirements": {},
        "exclusives": [],
        "grants": {
          "type": "permanent"
        }
      },
      "editorMeta": {
        "x": 1414,
        "y": 414,
        "group": "防御系",
        "locked": false,
        "editState": "done",
        "groupLabel": "防御系",
        "growthTrack": "defense",
        "growthTier": 2,
        "sourceSkillId": "skill_heal"
      },
      "speed": -2,
      "target": {
        "subject": "SUBJECT_SELF",
        "scope": "SCOPE_ENTITY",
        "selection": {
          "mode": "single",
          "candidateParts": [],
          "selectedParts": [],
          "selectCount": 1
        }
      },
      "requirements": {},
      "costs": {
        "ap": 2,
        "perTurnLimit": 1
      },
      "buffRefs": {
        "apply": [],
        "remove": []
      },
      "actions": [
        {
          "id": "action_1",
          "name": "Effect 1",
          "target": {
            "binding": {
              "mode": "follow",
              "ref": "skillTarget"
            }
          },
          "effect": {
            "effectType": "HEAL",
            "amount": 20,
            "amountType": "ABS"
          }
        }
      ]
    },
    {
      "id": "skill_savage_charge",
      "name": "应急护甲",
      "rarity": "Rare",
      "description": "应急防御。付出少量生命换取关键部位护甲，适合抢救即将被打穿的部位。",
      "prerequisites": [
        "skill_block"
      ],
      "unlock": {
        "cost": {
          "kp": 2
        },
        "requirements": {},
        "exclusives": [],
        "grants": {
          "type": "permanent"
        }
      },
      "editorMeta": {
        "x": 1114,
        "y": 614,
        "group": "防御系",
        "locked": false,
        "editState": "done",
        "groupLabel": "防御系",
        "growthTrack": "defense",
        "growthTier": 3,
        "sourceSkillId": "skill_savage_charge"
      },
      "speed": 2,
      "target": {
        "subject": "SUBJECT_SELF",
        "scope": "SCOPE_PART",
        "selection": {
          "mode": "single",
          "candidateParts": [
            "chest"
          ],
          "selectedParts": [
            "chest"
          ],
          "selectCount": 1
        }
      },
      "requirements": {
        "selfPart": {
          "mode": "ANY",
          "parts": [
            "leg"
          ],
          "mustBeUsable": true
        }
      },
      "costs": {
        "ap": 0,
        "partSlot": {
          "part": "leg",
          "slotCost": 2
        },
        "perTurnLimit": 1
      },
      "buffRefs": {
        "apply": [],
        "remove": []
      },
      "actions": [
        {
          "id": "action_1",
          "name": "扣血",
          "target": {
            "binding": {
              "mode": "explicit"
            },
            "spec": {
              "subject": "SUBJECT_SELF",
              "scope": "SCOPE_ENTITY",
              "selection": {
                "mode": "single",
                "candidateParts": [],
                "selectedParts": [],
                "selectCount": 1
              }
            }
          },
          "effect": {
            "effectType": "DMG_HP",
            "amount": 5,
            "amountType": "ABS"
          }
        },
        {
          "id": "action_2",
          "name": "加甲",
          "target": {
            "binding": {
              "mode": "follow",
              "ref": "skillTarget"
            }
          },
          "effect": {
            "effectType": "ARMOR_ADD",
            "amountType": "ABS",
            "amount": 20
          }
        }
      ]
    },
    {
      "id": "skill_regroup",
      "name": "受击备甲",
      "rarity": "Rare",
      "description": "防御姿态。受到攻击前先获得护甲，把敌人的进攻压力转成缓冲层。",
      "prerequisites": [
        "skill_artery_slice_copy_1769788322314"
      ],
      "unlock": {
        "cost": {
          "kp": 2
        },
        "requirements": {},
        "exclusives": [],
        "grants": {
          "type": "permanent"
        }
      },
      "editorMeta": {
        "x": 1014,
        "y": 614,
        "group": "防御系",
        "locked": false,
        "editState": "done",
        "groupLabel": "防御系",
        "growthTrack": "defense",
        "growthTier": 3,
        "sourceSkillId": "skill_regroup"
      },
      "speed": 10,
      "target": {
        "subject": "SUBJECT_SELF",
        "scope": "SCOPE_ENTITY",
        "selection": {
          "mode": "single",
          "candidateParts": [],
          "selectedParts": [],
          "selectCount": 1
        }
      },
      "requirements": {},
      "costs": {
        "ap": 1,
        "partSlot": {
          "part": "chest",
          "slotCost": 1
        },
        "perTurnLimit": 1
      },
      "buffRefs": {
        "remove": [],
        "apply": [
          {
            "buffId": "new_buff_1771485041778",
            "target": "self",
            "params": {
              "healArmorVal": 5
            }
          }
        ]
      },
      "actions": []
    },
    {
      "id": "skill_hold_the_line_copy_1769790933469",
      "name": "顺势回护",
      "rarity": "Rare",
      "description": "防守反打。造成少量伤害并回复手部护甲，让防御线具备轻量反击。",
      "prerequisites": [
        "skill_artery_slice_copy_1769788322314"
      ],
      "unlock": {
        "cost": {
          "kp": 3
        },
        "requirements": {},
        "exclusives": [],
        "grants": {
          "type": "permanent"
        }
      },
      "editorMeta": {
        "x": 914,
        "y": 614,
        "editState": "done",
        "group": "防御系",
        "locked": false,
        "groupLabel": "防御系",
        "growthTrack": "defense",
        "growthTier": 3,
        "sourceSkillId": "skill_hold_the_line_copy_1769790933469"
      },
      "speed": 2,
      "target": {
        "subject": "SUBJECT_ENEMY",
        "scope": "SCOPE_PART",
        "selection": {
          "mode": "single",
          "candidateParts": [
            "arm"
          ],
          "selectedParts": [],
          "selectCount": 1
        }
      },
      "requirements": {
        "selfPart": {
          "mode": "ANY",
          "parts": [
            "chest"
          ],
          "mustBeUsable": true
        }
      },
      "costs": {
        "ap": 1,
        "partSlot": {
          "part": "arm",
          "slotCost": 1
        },
        "perTurnLimit": 1
      },
      "buffRefs": {
        "apply": [
          {
            "buffId": "new_buff_1771482673293",
            "target": "self",
            "chance": 1,
            "duration": 1,
            "params": {
              "ArmorGetVal": 5
            }
          }
        ],
        "remove": []
      },
      "actions": [
        {
          "id": "action_1",
          "name": "造成伤害",
          "target": {
            "binding": {
              "mode": "follow",
              "ref": "skillTarget"
            }
          },
          "effect": {
            "effectType": "DMG_HP",
            "amountType": "ABS",
            "amount": 10
          }
        }
      ]
    },
    {
      "id": "skill_hold_the_line_copy_1769956923405",
      "name": "全身覆甲",
      "rarity": "Rare",
      "description": "范围防御。多个部位获得护甲，适合应对分散打击和持续消耗。",
      "prerequisites": [
        "skill_artery_slice_copy_1769789197982"
      ],
      "unlock": {
        "cost": {
          "kp": 3
        },
        "requirements": {},
        "exclusives": [],
        "grants": {
          "type": "permanent"
        }
      },
      "editorMeta": {
        "x": 1214,
        "y": 614,
        "editState": "done",
        "group": "防御系",
        "locked": false,
        "groupLabel": "防御系",
        "growthTrack": "defense",
        "growthTier": 3,
        "sourceSkillId": "skill_hold_the_line_copy_1769956923405"
      },
      "speed": 2,
      "target": {
        "subject": "SUBJECT_SELF",
        "scope": "SCOPE_PART",
        "selection": {
          "mode": "multiple",
          "candidateParts": [
            "head",
            "chest",
            "abdomen",
            "arm",
            "leg"
          ],
          "selectedParts": [
            "head",
            "chest",
            "abdomen",
            "arm",
            "leg"
          ],
          "selectCount": 5
        }
      },
      "requirements": {
        "selfPart": {
          "mode": "ANY",
          "parts": [
            "chest"
          ],
          "mustBeUsable": true
        }
      },
      "costs": {
        "ap": 2,
        "partSlot": {
          "part": "arm",
          "slotCost": 1
        },
        "perTurnLimit": 1
      },
      "buffRefs": {
        "apply": [],
        "remove": []
      },
      "actions": [
        {
          "id": "action_1",
          "name": "增加护甲",
          "target": {
            "binding": {
              "mode": "follow",
              "ref": "skillTarget"
            }
          },
          "effect": {
            "effectType": "ARMOR_ADD",
            "amountType": "ABS",
            "amount": 5
          }
        }
      ]
    },
    {
      "id": "skill_fortify",
      "name": "堡垒姿态",
      "rarity": "Epic",
      "description": "重型防御。立即获得大量护甲，并为下一轮继续恢复护甲做准备。",
      "prerequisites": [
        "skill_regroup"
      ],
      "unlock": {
        "cost": {
          "kp": 5
        },
        "requirements": {},
        "exclusives": [],
        "grants": {
          "type": "permanent"
        }
      },
      "editorMeta": {
        "x": 914,
        "y": 814,
        "group": "防御系",
        "locked": false,
        "editState": "done",
        "groupLabel": "防御系",
        "growthTrack": "defense",
        "growthTier": 4,
        "sourceSkillId": "skill_fortify"
      },
      "speed": 0,
      "target": {
        "subject": "SUBJECT_SELF",
        "scope": "SCOPE_ENTITY",
        "selection": {
          "mode": "single",
          "candidateParts": [
            "head",
            "chest",
            "abdomen",
            "arm",
            "leg"
          ],
          "selectedParts": [],
          "selectCount": 1
        }
      },
      "requirements": {
        "selfPart": {
          "mode": "ANY",
          "parts": [
            "chest"
          ],
          "mustBeUsable": true
        }
      },
      "costs": {
        "ap": 4,
        "partSlot": {
          "part": "head",
          "slotCost": 2
        },
        "perTurnLimit": 1
      },
      "buffRefs": {
        "apply": [
          {
            "buffId": "buff_ap_regen",
            "target": "self",
            "chance": 1,
            "duration": 1,
            "params": {
              "ArmorGetVal": 40,
              "buffDuration": 2
            }
          }
        ],
        "remove": []
      },
      "actions": [
        {
          "id": "action_1",
          "name": "Effect 1",
          "target": {
            "binding": {
              "mode": "follow",
              "ref": "skillTarget"
            }
          },
          "effect": {
            "effectType": "ARMOR_ADD",
            "amount": 40,
            "amountType": "ABS"
          }
        }
      ]
    },
    {
      "id": "skill_aegis",
      "name": "绝对防御",
      "rarity": "Legendary",
      "description": "关键防御。短时间内保护现有护甲，用来扛住敌人的爆发回合。",
      "prerequisites": [
        "skill_hit_me_if_you_dare"
      ],
      "unlock": {
        "cost": {
          "kp": 8
        },
        "requirements": {},
        "exclusives": [],
        "grants": {
          "type": "permanent"
        }
      },
      "editorMeta": {
        "x": 914,
        "y": 1014,
        "group": "防御系",
        "locked": false,
        "editState": "done",
        "groupLabel": "防御系",
        "growthTrack": "defense",
        "growthTier": 6,
        "sourceSkillId": "skill_aegis"
      },
      "speed": 10,
      "target": {
        "subject": "SUBJECT_SELF",
        "scope": "SCOPE_ENTITY",
        "selection": {
          "mode": "single",
          "candidateParts": [],
          "selectedParts": [],
          "selectCount": 1
        }
      },
      "requirements": {
        "selfPart": {
          "mode": "ANY",
          "parts": [
            "chest"
          ],
          "mustBeUsable": true
        }
      },
      "costs": {
        "ap": 5,
        "partSlot": {
          "part": "chest",
          "slotCost": 3
        },
        "perTurnLimit": 1
      },
      "buffRefs": {
        "apply": [
          {
            "buffId": "new_buff_1771481773827",
            "target": "self",
            "chance": 1,
            "duration": 1,
            "params": {}
          }
        ],
        "remove": []
      },
      "actions": []
    },
    {
      "id": "skill_hit_me_if_you_dare",
      "name": "反击架势",
      "rarity": "Epic",
      "description": "防反节点。进入反击姿态，被攻击后尝试还击，让防御不只是拖延。",
      "prerequisites": [
        "skill_fortify"
      ],
      "unlock": {
        "cost": {
          "kp": 5
        },
        "requirements": {},
        "exclusives": [],
        "grants": {
          "type": "permanent"
        }
      },
      "editorMeta": {
        "x": 914,
        "y": 914,
        "group": "防御系",
        "locked": false,
        "editState": "done",
        "groupLabel": "防御系",
        "growthTrack": "defense",
        "growthTier": 5,
        "sourceSkillId": "skill_hit_me_if_you_dare"
      },
      "speed": 4,
      "target": {
        "subject": "SUBJECT_SELF",
        "scope": "SCOPE_ENTITY",
        "selection": {
          "mode": "single",
          "candidateParts": [],
          "selectedParts": [],
          "selectCount": 1
        }
      },
      "requirements": {},
      "costs": {
        "ap": 2,
        "perTurnLimit": 1
      },
      "buffRefs": {
        "apply": [
          {
            "buffId": "buff_counter",
            "target": "self",
            "chance": 1,
            "duration": 1
          }
        ],
        "remove": []
      },
      "actions": []
    },
    {
      "id": "skill_play_dead_three_seconds",
      "name": "忍痛减伤",
      "rarity": "Epic",
      "description": "减伤防御。短时间内降低受到的伤害，适合处理无法完全挡住的攻击。",
      "prerequisites": [
        "skill_regroup"
      ],
      "unlock": {
        "cost": {
          "kp": 5
        },
        "requirements": {},
        "exclusives": [],
        "grants": {
          "type": "permanent"
        }
      },
      "editorMeta": {
        "x": 1014,
        "y": 814,
        "group": "防御系",
        "locked": false,
        "editState": "done",
        "groupLabel": "防御系",
        "growthTrack": "defense",
        "growthTier": 4,
        "sourceSkillId": "skill_play_dead_three_seconds"
      },
      "speed": 5,
      "target": {
        "subject": "SUBJECT_SELF",
        "scope": "SCOPE_ENTITY",
        "selection": {
          "mode": "single",
          "candidateParts": [],
          "selectedParts": [],
          "selectCount": 1
        }
      },
      "requirements": {},
      "costs": {
        "ap": 1,
        "perTurnLimit": 1
      },
      "buffRefs": {
        "apply": [
          {
            "buffId": "buff_pain_sup",
            "target": "self",
            "chance": 1,
            "duration": 2
          }
        ],
        "remove": []
      },
      "actions": []
    },
    {
      "id": "skill_cactus_vest",
      "name": "荆棘甲",
      "rarity": "Legendary",
      "description": "防御终局。防守后把部分伤害反弹给攻击者，形成以守转攻的完成形。",
      "prerequisites": [
        "skill_aegis"
      ],
      "unlock": {
        "cost": {
          "kp": 8
        },
        "requirements": {},
        "exclusives": [],
        "grants": {
          "type": "permanent"
        }
      },
      "editorMeta": {
        "x": 914,
        "y": 1114,
        "group": "防御系",
        "locked": false,
        "editState": "done",
        "groupLabel": "防御系",
        "growthTrack": "defense",
        "growthTier": 7,
        "sourceSkillId": "skill_cactus_vest"
      },
      "speed": 3,
      "target": {
        "subject": "SUBJECT_SELF",
        "scope": "SCOPE_ENTITY",
        "selection": {
          "mode": "single",
          "candidateParts": [],
          "selectedParts": [],
          "selectCount": 1
        }
      },
      "requirements": {},
      "costs": {
        "ap": 2,
        "perTurnLimit": 1
      },
      "buffRefs": {
        "apply": [
          {
            "buffId": "buff_thorns",
            "target": "self",
            "chance": 1,
            "duration": 3
          }
        ],
        "remove": []
      },
      "actions": []
    },
    {
      "id": "skill_skull_cracker_copy_1770042860426",
      "name": "疾步",
      "rarity": "Common",
      "description": "基础战术。提高自身速度，让玩家更容易抢到关键行动窗口。",
      "prerequisites": [],
      "unlock": {
        "cost": {
          "kp": 1
        },
        "requirements": {},
        "exclusives": [],
        "grants": {
          "type": "permanent"
        }
      },
      "editorMeta": {
        "x": 1614,
        "y": 214,
        "editState": "done",
        "group": "战术/AP系",
        "locked": false,
        "groupLabel": "战术/AP系",
        "growthTrack": "tempo",
        "growthTier": 1,
        "sourceSkillId": "skill_skull_cracker_copy_1770042860426"
      },
      "speed": -3,
      "target": {
        "subject": "SUBJECT_SELF",
        "scope": "SCOPE_ENTITY",
        "selection": {
          "mode": "single",
          "candidateParts": [],
          "selectedParts": [],
          "selectCount": 1
        }
      },
      "requirements": {
        "selfPart": {
          "mode": "ANY",
          "parts": [
            "arm"
          ],
          "mustBeUsable": true
        }
      },
      "costs": {
        "ap": 1,
        "partSlot": {
          "part": "arm",
          "slotCost": 2
        },
        "perTurnLimit": 1
      },
      "buffRefs": {
        "apply": [
          {
            "buffId": "new_buff_1771487521271",
            "target": "self",
            "params": {
              "speedUpVal": 2
            }
          }
        ],
        "remove": []
      },
      "actions": []
    },
    {
      "id": "skill_shockwave_copy_1770041956468",
      "name": "后撤步",
      "rarity": "Uncommon",
      "description": "防守战术。消耗腿部护甲换取免伤，为下一步回 AP 或爆发争取空间。",
      "prerequisites": [
        "skill_skull_cracker_copy_1770042860426"
      ],
      "unlock": {
        "cost": {
          "kp": 2
        },
        "requirements": {},
        "exclusives": [],
        "grants": {
          "type": "permanent"
        }
      },
      "editorMeta": {
        "x": 1614,
        "y": 414,
        "editState": "done",
        "group": "战术/AP系",
        "locked": false,
        "groupLabel": "战术/AP系",
        "growthTrack": "tempo",
        "growthTier": 2,
        "sourceSkillId": "skill_shockwave_copy_1770041956468"
      },
      "speed": 8,
      "target": {
        "subject": "SUBJECT_SELF",
        "scope": "SCOPE_PART",
        "selection": {
          "mode": "single",
          "candidateParts": [
            "leg"
          ],
          "selectedParts": [],
          "selectCount": 1
        }
      },
      "requirements": {
        "selfPart": {
          "mode": "ANY",
          "parts": [
            "chest"
          ],
          "mustBeUsable": true
        }
      },
      "costs": {
        "ap": 1,
        "partSlot": {
          "part": "chest",
          "slotCost": 2
        },
        "perTurnLimit": 1
      },
      "buffRefs": {
        "apply": [
          {
            "buffId": "new_buff_1771481773827",
            "target": "self",
            "chance": 1,
            "duration": 2,
            "params": {
              "buffDuration": 2,
              "stackNum": 1
            }
          }
        ],
        "remove": []
      },
      "actions": [
        {
          "id": "action_1",
          "name": "扣除护甲",
          "target": {
            "binding": {
              "mode": "follow",
              "ref": "skillTarget"
            }
          },
          "effect": {
            "effectType": "DMG_ARMOR",
            "amount": 5,
            "amountType": "ABS"
          }
        }
      ]
    },
    {
      "id": "skill_shockwave_copy_1769791396881",
      "name": "破盔回气",
      "rarity": "Rare",
      "description": "AP 节奏。舍弃头部护甲换取额外 AP，把防御资源转化为回合爆发。",
      "prerequisites": [
        "skill_shockwave_copy_1770041956468"
      ],
      "unlock": {
        "cost": {
          "kp": 3
        },
        "requirements": {},
        "exclusives": [],
        "grants": {
          "type": "permanent"
        }
      },
      "editorMeta": {
        "x": 1614,
        "y": 614,
        "editState": "done",
        "group": "战术/AP系",
        "locked": false,
        "groupLabel": "战术/AP系",
        "growthTrack": "tempo",
        "growthTier": 3,
        "sourceSkillId": "skill_shockwave_copy_1769791396881"
      },
      "speed": 2,
      "target": {
        "subject": "SUBJECT_SELF",
        "scope": "SCOPE_PART",
        "selection": {
          "mode": "single",
          "candidateParts": [
            "head"
          ],
          "selectedParts": [],
          "selectCount": 1
        }
      },
      "requirements": {
        "selfPart": {
          "mode": "ANY",
          "parts": [
            "chest"
          ],
          "mustBeUsable": true
        }
      },
      "costs": {
        "ap": 0,
        "perTurnLimit": 1
      },
      "buffRefs": {
        "apply": [],
        "remove": []
      },
      "actions": [
        {
          "id": "action_1",
          "name": "移除护甲",
          "target": {
            "binding": {
              "mode": "follow",
              "ref": "skillTarget"
            }
          },
          "effect": {
            "effectType": "DMG_ARMOR",
            "amount": 100,
            "amountType": "PCT_CURRENT"
          }
        },
        {
          "id": "action_2",
          "name": "获得行动点",
          "target": {
            "binding": {
              "mode": "follow",
              "ref": "skillTarget"
            }
          },
          "effect": {
            "effectType": "AP_GAIN",
            "amountType": "ABS",
            "amount": 3
          }
        }
      ]
    },
    {
      "id": "skill_aegis_copy_1770042764756",
      "name": "战术重构",
      "rarity": "Legendary",
      "description": "战术终局。降低后续技能 AP 消耗，让爆发回合能够连续出手。",
      "prerequisites": [
        "skill_shockwave_copy_1769791396881"
      ],
      "unlock": {
        "cost": {
          "kp": 8
        },
        "requirements": {},
        "exclusives": [],
        "grants": {
          "type": "permanent"
        }
      },
      "editorMeta": {
        "x": 1614,
        "y": 814,
        "editState": "done",
        "group": "战术/AP系",
        "locked": false,
        "groupLabel": "战术/AP系",
        "growthTrack": "tempo",
        "growthTier": 4,
        "sourceSkillId": "skill_aegis_copy_1770042764756"
      },
      "speed": 10,
      "target": {
        "subject": "SUBJECT_SELF",
        "scope": "SCOPE_ENTITY",
        "selection": {
          "mode": "single",
          "candidateParts": [],
          "selectedParts": [],
          "selectCount": 1
        }
      },
      "requirements": {
        "selfPart": {
          "mode": "ANY",
          "parts": [
            "chest"
          ],
          "mustBeUsable": true
        }
      },
      "costs": {
        "ap": 2,
        "partSlot": {
          "part": "chest",
          "slotCost": 3
        },
        "perTurnLimit": 1
      },
      "buffRefs": {
        "apply": [
          {
            "buffId": "new_buff_1771485482007",
            "target": "self",
            "params": {
              "apReduceVal": 1
            }
          }
        ],
        "remove": []
      },
      "actions": []
    }
  ]
}
